setup.py
django_hstore_flattenfields.egg-info/PKG-INFO
django_hstore_flattenfields.egg-info/SOURCES.txt
django_hstore_flattenfields.egg-info/dependency_links.txt
django_hstore_flattenfields.egg-info/not-zip-safe
django_hstore_flattenfields.egg-info/requires.txt
django_hstore_flattenfields.egg-info/top_level.txt
hstore_flattenfields/__init__.py
hstore_flattenfields/admin.py
hstore_flattenfields/models.py
hstore_flattenfields/signals.py
hstore_flattenfields/utils.py
hstore_flattenfields/db/__init__.py
hstore_flattenfields/db/aggregates.py
hstore_flattenfields/db/base.py
hstore_flattenfields/db/fields.py
hstore_flattenfields/db/manager.py
hstore_flattenfields/db/queryset.py
hstore_flattenfields/forms/__init__.py
hstore_flattenfields/forms/fields.py
hstore_flattenfields/forms/forms.py
hstore_flattenfields/forms/widgets.py
hstore_flattenfields/migrations/0001_initial.py
hstore_flattenfields/migrations/0002_add_field_contentpane_content_type.py
hstore_flattenfields/migrations/__init__.py
hstore_flattenfields/templatetags/__init__.py
hstore_flattenfields/templatetags/content_panes.py
tests/__init__.py
tests/local_settings.py
tests/manage.py
tests/runner.py
tests/settings.py
tests/urls.py
tests/wsgi.py
tests/app/__init__.py
tests/app/models.py
tests/app/tests/__init__.py
tests/app/tests/test_content_panes.py
tests/app/tests/test_dynamic_field_groups.py
tests/app/tests/test_forms.py
tests/app/tests/test_model_fields.py
tests/app/tests/test_queryset.py
tests/app/tests/test_types.py