Metadata-Version: 1.1
Name: django-hstore-flattenfields
Version: 0.8
Summary: Django with dynamic fields in hstore
Home-page: https://github.com/multmeio/django-hstore-flattenfields
Author: Luís Araújo
Author-email: caitifbrito@gmail.com
License: UNKNOWN
Platform: UNKNOWN
Classifier: Development Status :: 3 - Alpha
Classifier: Environment :: Web Environment
Classifier: Intended Audience :: Developers
Classifier: License :: OSI Approved :: BSD License
Classifier: Operating System :: OS Independent
Classifier: Programming Language :: Python
Classifier: Framework :: Django
